mcp_server_xigualaoshi/__init__.py
mcp_server_xigualaoshi/__main__.py
mcp_server_xigualaoshi/server.py
rents_mcp_server_weather-0.1.0.dist-info/METADATA
rents_mcp_server_weather-0.1.0.dist-info/WHEEL
rents_mcp_server_weather-0.1.0.dist-info/entry_points.txt
rents_mcp_server_weather-0.1.0.dist-info/top_level.txt
rents_mcp_server_weather-0.1.0.dist-info/RECORD
