Metadata-Version: 2.4
Name: rents-mcp-server-weather
Version: 0.1.0
Summary: Add your description here
Requires-Python: >=3.12
Requires-Dist: dotenv>=0.9.9
Requires-Dist: mcp>=1.18.0
Requires-Dist: openai>=2.4.0
